gsheet_df/__init__.py
gsheet_df/gsheet_API.py
gsheet_df-0.0.5.dist-info/LICENSE
gsheet_df-0.0.5.dist-info/METADATA
gsheet_df-0.0.5.dist-info/WHEEL
gsheet_df-0.0.5.dist-info/top_level.txt
gsheet_df-0.0.5.dist-info/RECORD
