Metadata-Version: 2.1
Name: gsheet-df
Version: 0.0.5
Summary: A personal package for downloading gsheet.
Home-page: https://github.com
Author: d_mok
Author-email: unknown@gmail.com
License: MIT
Platform: UNKNOWN
Classifier: Programming Language :: Python :: 3
Classifier: License :: OSI Approved :: MIT License
Classifier: Operating System :: OS Independent
Requires-Dist: pandas
